m3_dev_utils/__init__.py
m3_dev_utils/app_meta.py
m3_dev_utils/models.py
m3_dev_utils/plugin_meta.py
m3_dev_utils/django/__init__.py
m3_dev_utils/django/models/__init__.py
m3_dev_utils/django/models/export/__init__.py
m3_dev_utils/django/models/export/visual_paradigm/__init__.py
m3_dev_utils/django/models/export/visual_paradigm/actions.py
m3_dev_utils/django/models/export/visual_paradigm/download.js
m3_dev_utils/django/models/export/visual_paradigm/utils.py
m3_dev_utils/django/models/view/__init__.py
m3_dev_utils/django/models/view/actions.py
m3_dev_utils/django/models/view/list-window.js
m3_dev_utils/django/models/view/ui.py
m3_dev_utils/objectpack/__init__.py
m3_dev_utils/objectpack/listeners/__init__.py
m3_dev_utils/objectpack/listeners/actions.py
m3_dev_utils/objectpack/listeners/ui.py
m3_dev_utils/objectpack/listeners/utils.py
m3_dev_utils/objectpack/listeners/window.js
m3_dev_utils/pylint/__init__.py
m3_dev_utils/pylint/m3.py
m3_dev_utils/templates/m3-dev-utils/css.js
m3_dev_utils/utils/__init__.py
m3_dev_utils/utils/dependency.py
m3_dev_utils/utils/filesystem.py
m3_dev_utils/utils/misc.py
m3_dev_utils/utils/objectpack.py
m3_dev_utils/utils/ui.py
m3_dev_utils-0.8.0.dist-info/METADATA
m3_dev_utils-0.8.0.dist-info/WHEEL
m3_dev_utils-0.8.0.dist-info/dependency_links.txt
m3_dev_utils-0.8.0.dist-info/top_level.txt
m3_dev_utils-0.8.0.dist-info/RECORD
