Metadata-Version: 2.4
Name: m3-dev-utils
Version: 0.8.0
Summary: Инструментарий разработчика веб-приложений на платформе M3.
Home-page: https://stash.bars-open.ru/projects/M3/repos/m3-dev-utils
Author: Andrey Chagochkin
Author-email: andrey.chagochkin@bars-open.ru
Classifier: Intended Audience :: Developers
Classifier: Environment :: Web Environment
Classifier: Natural Language :: Russian
Classifier: Operating System :: OS Independent
Classifier: Programming Language :: Python
Classifier: Programming Language :: Python :: 2.7
Classifier: Programming Language :: Python :: 3.6
Classifier: Development Status :: 5 - Production/Stable
Classifier: Framework :: Django :: 1.9
Classifier: Framework :: Django :: 1.10
Classifier: Framework :: Django :: 1.11
Requires-Dist: six
Requires-Dist: lxml
Requires-Dist: django<2,>=1.8; python_version == "2.7"
Requires-Dist: django<2,>=1.11; python_version == "3.6"
Requires-Dist: m3-builder<2,>=1.2; python_version == "2.7"
Requires-Dist: m3-core<3,>=2; python_version == "2.7"
Requires-Dist: m3-ui<3,>=2; python_version == "2.7"
Requires-Dist: m3-objectpack<3,>=2; python_version == "2.7"
Requires-Dist: m3-builder<2,>=1.2; python_version == "3.6"
Requires-Dist: m3-core<3,>=2.2.16; python_version == "3.6"
Requires-Dist: m3-ui<3,>=2.2.40; python_version == "3.6"
Requires-Dist: m3-objectpack<3,>=2.2.18; python_version == "3.6"
Requires-Dist: m3_django_compatibility<2,>=1.12.0
Requires-Dist: pathlib2; python_version == "2.7"
Dynamic: author
Dynamic: author-email
Dynamic: classifier
Dynamic: home-page
Dynamic: requires-dist
Dynamic: summary
